AUTHORS
LICENSE
README.md
pyproject.toml
ovhai/__init__.py
ovhai/client.py
ovhai/errors.py
ovhai/ovhai_types.py
ovhai/py.typed
ovhai/setup.py
ovhai.egg-info/PKG-INFO
ovhai.egg-info/SOURCES.txt
ovhai.egg-info/dependency_links.txt
ovhai.egg-info/not-zip-safe
ovhai.egg-info/requires.txt
ovhai.egg-info/top_level.txt
ovhai/api/__init__.py
ovhai/api/app/__init__.py
ovhai/api/app/app_cli_command.py
ovhai/api/app/app_edit.py
ovhai/api/app/app_edit_label.py
ovhai/api/app/app_log.py
ovhai/api/app/app_start.py
ovhai/api/app/app_stop.py
ovhai/api/app/app_update.py
ovhai/api/app/app_update_image.py
ovhai/api/app/delete_v1_app_id.py
ovhai/api/app/get_v1_app.py
ovhai/api/app/get_v1_app_id.py
ovhai/api/app/post_v1_app.py
ovhai/api/app/post_v1_app_app_id_datasync.py
ovhai/api/capabilities/__init__.py
ovhai/api/capabilities/get_v1_capabilities_app_image.py
ovhai/api/capabilities/get_v1_capabilities_flavor.py
ovhai/api/capabilities/get_v1_capabilities_flavor_id.py
ovhai/api/capabilities/get_v1_capabilities_job_image.py
ovhai/api/capabilities/get_v1_capabilities_notebook_editor.py
ovhai/api/capabilities/get_v1_capabilities_notebook_editor_id.py
ovhai/api/capabilities/get_v1_capabilities_notebook_framework.py
ovhai/api/capabilities/get_v1_capabilities_notebook_framework_id.py
ovhai/api/capabilities/get_v1_capabilities_preset.py
ovhai/api/capabilities/get_v1_capabilities_preset_id.py
ovhai/api/capabilities/get_v1_capabilities_quota.py
ovhai/api/deprecated_capabilities/__init__.py
ovhai/api/deprecated_capabilities/get_v1_notebook_capabilities_editor.py
ovhai/api/deprecated_capabilities/get_v1_notebook_capabilities_editor_id.py
ovhai/api/deprecated_capabilities/get_v1_notebook_capabilities_framework.py
ovhai/api/deprecated_capabilities/get_v1_notebook_capabilities_framework_id.py
ovhai/api/framework/__init__.py
ovhai/api/framework/delete_v1_framework_id.py
ovhai/api/framework/get_v1_framework.py
ovhai/api/framework/get_v1_framework_id.py
ovhai/api/framework/patch_v1_framework_id.py
ovhai/api/framework/post_v1_framework.py
ovhai/api/image/__init__.py
ovhai/api/image/delete_v1_image_image_id.py
ovhai/api/image/delete_v1_image_image_id_version_tag.py
