Metadata-Version: 2.1
Name: ovhai
Version: 0.1a4
Summary: A client library for accessing OVHcloud's AI Solutions
Home-page: UNKNOWN
License: Apache-2.0
Project-URL: Repository, https://github.com/ovh/ovhai-python-sdk
Keywords: ovhai ovh AI
Platform: UNKNOWN
Requires-Python: >=3.8, <4
